odoo8_addon_sale_order_unified_menu-8.0.1.0.0.99.dev11-py2.7-nspkg.pth
odoo8_addon_sale_order_unified_menu-8.0.1.0.0.99.dev11.dist-info/METADATA
odoo8_addon_sale_order_unified_menu-8.0.1.0.0.99.dev11.dist-info/RECORD
odoo8_addon_sale_order_unified_menu-8.0.1.0.0.99.dev11.dist-info/WHEEL
odoo8_addon_sale_order_unified_menu-8.0.1.0.0.99.dev11.dist-info/namespace_packages.txt
odoo8_addon_sale_order_unified_menu-8.0.1.0.0.99.dev11.dist-info/top_level.txt
odoo_addons/sale_order_unified_menu/README.rst
odoo_addons/sale_order_unified_menu/__init__.py
odoo_addons/sale_order_unified_menu/__openerp__.py
odoo_addons/sale_order_unified_menu/i18n/it.po
odoo_addons/sale_order_unified_menu/i18n/sale_order_unified_menu.pot
odoo_addons/sale_order_unified_menu/i18n/sl.po
odoo_addons/sale_order_unified_menu/i18n/tr_TR.po
odoo_addons/sale_order_unified_menu/static/description/icon.png
odoo_addons/sale_order_unified_menu/views/sale_view.xml
