Metadata-Version: 2.1
Name: odoo8-addon-sale-order-unified-menu
Version: 8.0.1.0.0.99.dev11
Summary: Sale Order Unified Menu
Home-page: https://www.apuliasoftware.it
Author: Francesco Apruzzese
Author-email: UNKNOWN
License: AGPL-3
Platform: UNKNOWN
Classifier: Programming Language :: Python
Classifier: Framework :: Odoo
Classifier: License :: OSI Approved :: GNU Affero General Public License v3
Requires-Python: ~=2.7
Requires-Dist: odoo (<9.0a,>=8.0a)
